tsfm_client/__init__.py
tsfm_client/client.py
tsfm_client/models.py
tsfm_client-0.2.2.dist-info/METADATA
tsfm_client-0.2.2.dist-info/WHEEL
tsfm_client-0.2.2.dist-info/RECORD
