Metadata-Version: 2.3
Name: tsfm-client
Version: 0.2.2
Summary: Python client for TSFM time series forecasting with numpy support, confidence intervals, and multivariate predictions
License: MIT
Keywords: time-series,forecasting,foundation-models,api-client,numpy,multivariate,confidence-intervals,tsfm,chronos,toto
Author: Andrei Chernov
Author-email: chernov.andrey.998@gmail.com
Requires-Python: >=3.10
Classifier: Development Status :: 3 - Alpha
Classifier: Intended Audience :: Developers
Classifier: License :: OSI Approved :: MIT License
Classifier: Programming Language :: Python :: 3
Classifier: Programming Language :: Python :: 3.10
Classifier: Programming Language :: Python :: 3.11
Classifier: Programming Language :: Python :: 3.12
Classifier: Programming Language :: Python :: 3.13
Classifier: Programming Language :: Python :: 3.9
Classifier: Topic :: Scientific/Engineering :: Artificial Intelligence
Requires-Dist: httpx (>=0.25.0,<0.26.0)
Requires-Dist: matplotlib (>=3.10.5,<4.0.0)
Requires-Dist: notebook (>=7.4.4,<8.0.0)
Requires-Dist: numpy (>=1.24.0,<2.0.0)
Requires-Dist: pandas (>=2.0.0,<3.0.0)
Requires-Dist: pydantic (>=2.5.0,<3.0.0)
Requires-Dist: typing-extensions (>=4.8.0,<5.0.0)
Project-URL: Homepage, https://github.com/S-FM/tsfm-python-client
Project-URL: Repository, https://github.com/S-FM/tsfm-python-client
